ImgAlter/img_cut.py
ImgAlter-0.1.8.dist-info/METADATA
ImgAlter-0.1.8.dist-info/WHEEL
ImgAlter-0.1.8.dist-info/top_level.txt
ImgAlter-0.1.8.dist-info/RECORD
