Metadata-Version: 2.1
Name: ImgAlter
Version: 0.1.8
Summary: 1.Resize the image, 2.image transfer pdf
Home-page: https://github.com/tyj-1995
Author: White.tie
Author-email: 1042798703@qq.com
License: UNKNOWN
Platform: UNKNOWN
Classifier: Environment :: Web Environment
Classifier: Intended Audience :: Developers
Classifier: Operating System :: OS Independent
Classifier: Topic :: Text Processing :: Indexing
Classifier: Topic :: Utilities
Classifier: Topic :: Internet
Classifier: Topic :: Software Development :: Libraries :: Python Modules
Classifier: Programming Language :: Python
Classifier: Programming Language :: Python :: 2.6
Classifier: Programming Language :: Python :: 3.6
Requires-Dist: pillow (>=8.0.1)
Requires-Dist: python-magic-bin (==0.4.14)
